rst_in_md/__init__.py
rst_in_md/conversion.py
rst_in_md/extension.py
rst_in_md/processor.py
rst_in_md/superfence.py
rst_in_md-0.2.1.dist-info/METADATA
rst_in_md-0.2.1.dist-info/WHEEL
rst_in_md-0.2.1.dist-info/licenses/LICENSE
rst_in_md-0.2.1.dist-info/RECORD
