Metadata-Version: 2.3
Name: rst-in-md
Version: 0.2.1
Summary: Convert reStructuredText within Markdown to HTML.
Project-URL: Documentation, https://sebpretzer.github.io/rst-in-md/
Project-URL: Source, https://github.com/sebpretzer/rst-in-md
Author-email: Seb Pretzer <24555985+sebpretzer@users.noreply.github.com>
License: MIT License
License-File: LICENSE
Classifier: License :: OSI Approved :: MIT License
Classifier: Operating System :: OS Independent
Classifier: Programming Language :: Python :: 3
Requires-Python: <3.13,>=3.9
Requires-Dist: beautifulsoup4>=4.12.0
Requires-Dist: docutils>=0.21.0
Requires-Dist: markdown>=3.5.0
Provides-Extra: ci
Requires-Dist: pre-commit>=3.0.0; extra == 'ci'
Provides-Extra: docs
Requires-Dist: mkdocs-git-revision-date-localized-plugin>=1.2.0; extra == 'docs'
Requires-Dist: mkdocs-material>=9.0.0; extra == 'docs'
Requires-Dist: mkdocs>=1.5.0; extra == 'docs'
Requires-Dist: mkdocstrings[python]>=0.12.0; extra == 'docs'
Provides-Extra: publishing
Requires-Dist: hatch>=1.12.0; extra == 'publishing'
Provides-Extra: pymdownx
Requires-Dist: pymdown-extensions>=10.0.0; extra == 'pymdownx'
Provides-Extra: test
Requires-Dist: pytest>=7.0.0; extra == 'test'
